<annotation>
	<folder>train</folder>
	<filename>cd34152e-57ec-11ed-9f4a-0695fd3131fe.jpg</filename>
	<path>C:\Users\Robin\Desktop\FR\back\assets\unsorted\images\train\cd34152e-57ec-11ed-9f4a-0695fd3131fe.jpg</path>
	<source>
		<database>Unknown</database>
	</source>
	<size>
		<width>1920</width>
		<height>1080</height>
		<depth>3</depth>
	</size>
	<segmented>0</segmented>
	<object>
		<name>multimeter</name>
		<pose>Unspecified</pose>
		<truncated>0</truncated>
		<difficult>0</difficult>
		<bndbox>
			<xmin>554</xmin>
			<ymin>198</ymin>
			<xmax>984</xmax>
			<ymax>734</ymax>
		</bndbox>
	</object>
</annotation>
